{"assets/assets/bunnyhop/web_1.2.1/Build/UnityLoader.js":["assets/assets/bunnyhop/web_1.2.1/Build/UnityLoader.js"],"assets/assets/bunnyhop/web_1.2.1/Build/web_1.2.1.asm.code.unityweb":["assets/assets/bunnyhop/web_1.2.1/Build/web_1.2.1.asm.code.unityweb"],"assets/assets/bunnyhop/web_1.2.1/Build/web_1.2.1.asm.framework.unityweb":["assets/assets/bunnyhop/web_1.2.1/Build/web_1.2.1.asm.framework.unityweb"],"assets/assets/bunnyhop/web_1.2.1/Build/web_1.2.1.asm.memory.unityweb":["assets/assets/bunnyhop/web_1.2.1/Build/web_1.2.1.asm.memory.unityweb"],"assets/assets/bunnyhop/web_1.2.1/Build/web_1.2.1.data.unityweb":["assets/assets/bunnyhop/web_1.2.1/Build/web_1.2.1.data.unityweb"],"assets/assets/bunnyhop/web_1.2.1/Build/web_1.2.1.json":["assets/assets/bunnyhop/web_1.2.1/Build/web_1.2.1.json"],"assets/assets/bunnyhop/web_1.2.1/TemplateData/UnityProgress.js":["assets/assets/bunnyhop/web_1.2.1/TemplateData/UnityProgress.js"],"assets/assets/bunnyhop/web_1.2.1/TemplateData/favicon.ico":["assets/assets/bunnyhop/web_1.2.1/TemplateData/favicon.ico"],"assets/assets/bunnyhop/web_1.2.1/TemplateData/fullscreen.png":["assets/assets/bunnyhop/web_1.2.1/TemplateData/fullscreen.png"],"assets/assets/bunnyhop/web_1.2.1/TemplateData/progressEmpty.Dark.png":["assets/assets/bunnyhop/web_1.2.1/TemplateData/progressEmpty.Dark.png"],"assets/assets/bunnyhop/web_1.2.1/TemplateData/progressEmpty.Light.png":["assets/assets/bunnyhop/web_1.2.1/TemplateData/progressEmpty.Light.png"],"assets/assets/bunnyhop/web_1.2.1/TemplateData/progressFull.Dark.png":["assets/assets/bunnyhop/web_1.2.1/TemplateData/progressFull.Dark.png"],"assets/assets/bunnyhop/web_1.2.1/TemplateData/progressFull.Light.png":["assets/assets/bunnyhop/web_1.2.1/TemplateData/progressFull.Light.png"],"assets/assets/bunnyhop/web_1.2.1/TemplateData/progressLogo.Dark.png":["assets/assets/bunnyhop/web_1.2.1/TemplateData/progressLogo.Dark.png"],"assets/assets/bunnyhop/web_1.2.1/TemplateData/progressLogo.Light.png":["assets/assets/bunnyhop/web_1.2.1/TemplateData/progressLogo.Light.png"],"assets/assets/bunnyhop/web_1.2.1/TemplateData/style.css":["assets/assets/bunnyhop/web_1.2.1/TemplateData/style.css"],"assets/assets/bunnyhop/web_1.2.1/TemplateData/webgl-logo.png":["assets/assets/bunnyhop/web_1.2.1/TemplateData/webgl-logo.png"],"assets/assets/bunnyhop/web_1.2.1/index.html":["assets/assets/bunnyhop/web_1.2.1/index.html"],"assets/fonts/MaterialIcons-Regular.otf":["assets/fonts/MaterialIcons-Regular.otf"],"packages/cupertino_icons/assets/CupertinoIcons.ttf":["packages/cupertino_icons/assets/CupertinoIcons.ttf"],"packages/flutter_inappwebview/assets/t_rex_runner/t-rex.css":["packages/flutter_inappwebview/assets/t_rex_runner/t-rex.css"],"packages/flutter_inappwebview/assets/t_rex_runner/t-rex.html":["packages/flutter_inappwebview/assets/t_rex_runner/t-rex.html"],"packages/flutter_inappwebview_web/assets/web/web_support.js":["packages/flutter_inappwebview_web/assets/web/web_support.js"]}